mnnai/AsyncAI.py
mnnai/Generator.py
mnnai/SyncAI.py
mnnai/__init__.py
mnnai-5.4.0.dist-info/LICENSE
mnnai-5.4.0.dist-info/METADATA
mnnai-5.4.0.dist-info/WHEEL
mnnai-5.4.0.dist-info/top_level.txt
mnnai-5.4.0.dist-info/RECORD
