Metadata-Version: 2.1
Name: mnnai
Version: 5.4.0
Summary: Module for using MNN API
Home-page: https://github.com/mkshustov/MNNAI
Author: mkshustov
Author-email: reverse.api.mnn@gmail.com
Project-URL: Documentation, https://github.com/mkshustov/MNNAI
Project-URL: Site, https://mnnai.ru
Keywords: ai MNN chatgpt mnnai mnn
Classifier: Programming Language :: Python :: 3.11
Classifier: License :: OSI Approved :: MIT License
Classifier: Operating System :: OS Independent
Requires-Python: >=3.7
License-File: LICENSE
Requires-Dist: requests >=2.25.1
Requires-Dist: aiohttp
